MANIFEST.in
README.md
setup.py
michelanglo_protein/__init__.py
michelanglo_protein/alphafold2_retrieval.py
michelanglo_protein/apriori_effect.py
michelanglo_protein/core.py
michelanglo_protein/generate_AA_MCS.py
michelanglo_protein/gnomad_variant.py
michelanglo_protein/metadata_from_PDBe.py
michelanglo_protein/mutation.py
michelanglo_protein/protein_analysis.py
michelanglo_protein/protein_manual.py
michelanglo_protein/settings_handler.py
michelanglo_protein/structure.py
michelanglo_protein/swissmodel_retrieval.py
michelanglo_protein/to_reimplement.py
michelanglo_protein/unitests.py
michelanglo_protein.egg-info/PKG-INFO
michelanglo_protein.egg-info/SOURCES.txt
michelanglo_protein.egg-info/dependency_links.txt
michelanglo_protein.egg-info/requires.txt
michelanglo_protein.egg-info/top_level.txt
michelanglo_protein/analyse/Biopython_StructureAnalyser.py
michelanglo_protein/analyse/Pymol_StructureAnalyser.py
michelanglo_protein/analyse/__init__.py
michelanglo_protein/analyse/consurf.py
michelanglo_protein/analyse/pyrosetta_modifier/__init__.py
michelanglo_protein/analyse/pyrosetta_modifier/base.py
michelanglo_protein/analyse/pyrosetta_modifier/constraints.py
michelanglo_protein/analyse/pyrosetta_modifier/description.py
michelanglo_protein/analyse/pyrosetta_modifier/initialize.py
michelanglo_protein/analyse/pyrosetta_modifier/neighbors.py
michelanglo_protein/analyse/pyrosetta_modifier/relax.py
michelanglo_protein/analyse/pyrosetta_modifier/test.py
michelanglo_protein/analyse/pyrosetta_modifier/params/UNK.params
michelanglo_protein/analyse/pyrosetta_modifier/params/__init__.py
michelanglo_protein/generate/ET_monkeypatch.py
michelanglo_protein/generate/PDB_blast.py
michelanglo_protein/generate/__init__.py
michelanglo_protein/generate/_protein_base_mixin.py
michelanglo_protein/generate/_protein_disused_mixin.py
michelanglo_protein/generate/_protein_gatherer.py
michelanglo_protein/generate/_protein_uniprot_mixin.py
michelanglo_protein/generate/_proteome_gatherer.py
michelanglo_protein/generate/old_split_gnomAD.py
michelanglo_protein/generate/protParam_mod.py
michelanglo_protein/generate/split_ClinVar.py
michelanglo_protein/generate/split_gnomAD.py
